bespokelabs/__init__.py
bespokelabs/_base_client.py
bespokelabs/_client.py
bespokelabs/_compat.py
bespokelabs/_constants.py
bespokelabs/_exceptions.py
bespokelabs/_files.py
bespokelabs/_models.py
bespokelabs/_qs.py
bespokelabs/_resource.py
bespokelabs/_response.py
bespokelabs/_streaming.py
bespokelabs/_types.py
bespokelabs/_version.py
bespokelabs/py.typed
bespokelabs/_utils/__init__.py
bespokelabs/_utils/_logs.py
bespokelabs/_utils/_proxy.py
bespokelabs/_utils/_reflection.py
bespokelabs/_utils/_streams.py
bespokelabs/_utils/_sync.py
bespokelabs/_utils/_transform.py
bespokelabs/_utils/_typing.py
bespokelabs/_utils/_utils.py
bespokelabs/lib/.keep
bespokelabs/resources/__init__.py
bespokelabs/resources/minicheck/__init__.py
bespokelabs/resources/minicheck/factcheck.py
bespokelabs/resources/minicheck/minicheck.py
bespokelabs/types/__init__.py
bespokelabs/types/minicheck/__init__.py
bespokelabs/types/minicheck/factcheck_create_params.py
bespokelabs/types/minicheck/factcheck_create_response.py
bespokelabs-0.2.3.dist-info/METADATA
bespokelabs-0.2.3.dist-info/WHEEL
bespokelabs-0.2.3.dist-info/licenses/LICENSE
bespokelabs-0.2.3.dist-info/RECORD
